holyshit/__init__.py
holyshit/client.py
holyshit/exceptions.py
holyshit-1.2.0.dist-info/LICENSE
holyshit-1.2.0.dist-info/WHEEL
holyshit-1.2.0.dist-info/METADATA
holyshit-1.2.0.dist-info/RECORD
