Metadata-Version: 2.1
Name: holyshit
Version: 1.2.0
Summary: Asynchronous experimental wrapper for the holyshit.wtf API
License: MIT
Author: cobaltgit
Author-email: criterion@chitco.co.uk
Requires-Python: >=3.8,<4.0
Classifier: License :: OSI Approved :: MIT License
Classifier: Programming Language :: Python :: 3
Classifier: Programming Language :: Python :: 3.10
Classifier: Programming Language :: Python :: 3.8
Classifier: Programming Language :: Python :: 3.9
Requires-Dist: aiohttp (>=3.6.0)
